pyvie.py
pyvie-1.0.0.dist-info/LICENSE.txt
pyvie-1.0.0.dist-info/METADATA
pyvie-1.0.0.dist-info/RECORD
pyvie-1.0.0.dist-info/WHEEL
pyvie-1.0.0.dist-info/top_level.txt
