Metadata-Version: 2.1
Name: pyvie
Version: 1.0.0
Summary: A module for making videos in Python
Home-page: UNKNOWN
Author: UNKNOWN
Author-email: davidbutts96@gmail.com
License: UNKNOWN
Keywords: Python movies animation
Platform: UNKNOWN
Requires-Dist: matplotlib
Requires-Dist: Ipython
